bridgestan/__init__.py
bridgestan/__version.py
bridgestan/compile.py
bridgestan/download.py
bridgestan/model.py
bridgestan/py.typed
bridgestan/util.py
bridgestan-2.7.0.dist-info/METADATA
bridgestan-2.7.0.dist-info/WHEEL
bridgestan-2.7.0.dist-info/top_level.txt
bridgestan-2.7.0.dist-info/RECORD
