Metadata-Version: 2.4
Name: bridgestan
Version: 2.7.0
Summary: Access the methods of a Stan model in Python.
Author-email: Brian Ward <bward@flatironinstitute.org>, Bob Carpenter <bcarpenter@flatironinstitute.org>, Edward Roualdes <eroualdes@csuchico.edu>
License: BSD-3-Clause
Project-URL: Homepage, https://github.com/roualdes/bridgestan
Project-URL: Bug Tracker, https://github.com/roualdes/bridgestan/issues
Requires-Python: >=3.9
Requires-Dist: numpy
Requires-Dist: dllist~=2.0.0
Requires-Dist: stanio~=0.5.1
Provides-Extra: test
Requires-Dist: pandas; extra == "test"
Requires-Dist: pytest; extra == "test"
Requires-Dist: pytest-cov; extra == "test"
